forgeserver/__init__.py
forgeserver/__main__.py
forgeserver/_subprocess.py
forgeserver/_types.py
forgeserver/config.py
forgeserver/importer.py
forgeserver/logging.py
forgeserver/main.py
forgeserver/py.typed
forgeserver/server.py
forgeserver/lifespan/__init__.py
forgeserver/lifespan/off.py
forgeserver/lifespan/on.py
forgeserver/loops/__init__.py
forgeserver/loops/asyncio.py
forgeserver/loops/auto.py
forgeserver/loops/uvloop.py
forgeserver/middleware/__init__.py
forgeserver/middleware/message_logger.py
forgeserver/middleware/proxy_headers.py
forgeserver/middleware/wsgi.py
forgeserver/protocols/__init__.py
forgeserver/protocols/utils.py
forgeserver/protocols/http/__init__.py
forgeserver/protocols/http/auto.py
forgeserver/protocols/http/flow_control.py
forgeserver/protocols/http/h11_impl.py
forgeserver/protocols/http/httptools_impl.py
forgeserver/protocols/websockets/__init__.py
forgeserver/protocols/websockets/auto.py
forgeserver/protocols/websockets/websockets_impl.py
forgeserver/protocols/websockets/wsproto_impl.py
forgeserver/supervisors/__init__.py
forgeserver/supervisors/basereload.py
forgeserver/supervisors/multiprocess.py
forgeserver/supervisors/statreload.py
forgeserver/supervisors/watchfilesreload.py
forgeserver/supervisors/watchgodreload.py
forgeserver/tests/__init__.py
forgeserver/tests/conftest.py
forgeserver/tests/response.py
forgeserver/tests/test_auto_detection.py
forgeserver/tests/test_cli.py
forgeserver/tests/test_config.py
forgeserver/tests/test_default_headers.py
forgeserver/tests/test_lifespan.py
forgeserver/tests/test_main.py
forgeserver/tests/test_server.py
forgeserver/tests/test_ssl.py
forgeserver/tests/test_subprocess.py
forgeserver/tests/utils.py
forgeserver/tests/importer/__init__.py
forgeserver/tests/importer/circular_import_a.py
forgeserver/tests/importer/circular_import_b.py
forgeserver/tests/importer/raise_import_error.py
forgeserver/tests/importer/test_importer.py
forgeserver/tests/middleware/__init__.py
forgeserver-0.0.11.dist-info/METADATA
forgeserver-0.0.11.dist-info/WHEEL
forgeserver-0.0.11.dist-info/entry_points.txt
forgeserver-0.0.11.dist-info/RECORD
