Metadata-Version: 2.3
Name: forgeserver
Version: 0.0.11
Summary: An awesome package is coming soon! 🎉
Project-URL: Homepage, https://github.com/Kludex/siteforge
Project-URL: Source, https://github.com/Kludex/siteforge
Project-URL: Twitter, https://twitter.com/marcelotryle
Project-URL: Funding, https://github.com/sponsors/Kludex
Author-email: Marcelo Trylesinski <marcelotryle@gmail.com>
License: MIT
Classifier: Development Status :: 3 - Alpha
Classifier: Intended Audience :: Developers
Classifier: License :: OSI Approved :: MIT License
Classifier: Natural Language :: English
Classifier: Operating System :: OS Independent
Classifier: Programming Language :: Python :: 3
Classifier: Programming Language :: Python :: 3 :: Only
Classifier: Programming Language :: Python :: 3.8
Classifier: Programming Language :: Python :: 3.9
Classifier: Programming Language :: Python :: 3.10
Classifier: Programming Language :: Python :: 3.11
Classifier: Programming Language :: Python :: 3.12
Classifier: Programming Language :: Python :: 3.13
Requires-Python: >=3.8
Requires-Dist: click>=7.0
Requires-Dist: h11>=0.8
Requires-Dist: typing-extensions>=4.0; python_version < '3.11'
Provides-Extra: standard
Requires-Dist: colorama>=0.4; (sys_platform == 'win32') and extra == 'standard'
Requires-Dist: httptools>=0.6.3; extra == 'standard'
Requires-Dist: python-dotenv>=0.13; extra == 'standard'
Requires-Dist: pyyaml>=5.1; extra == 'standard'
Requires-Dist: uvloop!=0.15.0,!=0.15.1,>=0.14.0; (sys_platform != 'win32' and (sys_platform != 'cygwin' and platform_python_implementation != 'PyPy')) and extra == 'standard'
Requires-Dist: watchfiles>=0.13; extra == 'standard'
Requires-Dist: websockets>=10.4; extra == 'standard'
